fast_gov_uk/__init__.py
fast_gov_uk/core.py
fast_gov_uk/forms.py
fast_gov_uk/assets/VERSION.txt
fast_gov_uk/assets/govuk-frontend-5.11.1.min.css
fast_gov_uk/assets/govuk-frontend-5.11.1.min.css.map
fast_gov_uk/assets/govuk-frontend-5.11.1.min.js
fast_gov_uk/assets/govuk-frontend-5.11.1.min.js.map
fast_gov_uk/assets/assets/manifest.json
fast_gov_uk/assets/assets/fonts/bold-affa96571d-v2.woff
fast_gov_uk/assets/assets/fonts/bold-b542beb274-v2.woff2
fast_gov_uk/assets/assets/fonts/light-94a07e06a1-v2.woff2
fast_gov_uk/assets/assets/fonts/light-f591b13f7d-v2.woff
fast_gov_uk/assets/assets/images/favicon.ico
fast_gov_uk/assets/assets/images/favicon.svg
fast_gov_uk/assets/assets/images/govuk-crest.svg
fast_gov_uk/assets/assets/images/govuk-icon-180.png
fast_gov_uk/assets/assets/images/govuk-icon-192.png
fast_gov_uk/assets/assets/images/govuk-icon-512.png
fast_gov_uk/assets/assets/images/govuk-icon-mask.svg
fast_gov_uk/assets/assets/images/govuk-opengraph-image.png
fast_gov_uk/assets/assets/rebrand/manifest.json
fast_gov_uk/assets/assets/rebrand/images/favicon.ico
fast_gov_uk/assets/assets/rebrand/images/favicon.svg
fast_gov_uk/assets/assets/rebrand/images/govuk-crest.svg
fast_gov_uk/assets/assets/rebrand/images/govuk-icon-180.png
fast_gov_uk/assets/assets/rebrand/images/govuk-icon-192.png
fast_gov_uk/assets/assets/rebrand/images/govuk-icon-512.png
fast_gov_uk/assets/assets/rebrand/images/govuk-icon-mask.svg
fast_gov_uk/assets/assets/rebrand/images/govuk-opengraph-image.png
fast_gov_uk/design_system/__init__.py
fast_gov_uk/design_system/components.py
fast_gov_uk/design_system/contrib.py
fast_gov_uk/design_system/inputs.py
fast_gov_uk/design_system/navigation.py
fast_gov_uk/design_system/pages.py
fast_gov_uk/design_system/typography.py
fast_gov_uk/design_system/utils.py
fast_gov_uk/tests/__init__.py
fast_gov_uk/tests/app.py
fast_gov_uk/tests/conftest.py
fast_gov_uk/tests/picture.png
fast_gov_uk/tests/test_core.py
fast_gov_uk/tests/test_forms.py
fast_gov_uk-0.7.3.dist-info/METADATA
fast_gov_uk-0.7.3.dist-info/WHEEL
fast_gov_uk-0.7.3.dist-info/licenses/LICENSE
fast_gov_uk-0.7.3.dist-info/RECORD
