Metadata-Version: 2.4
Name: fast-gov-uk
Version: 0.7.3
Summary: A toolkit for rapid development of simple gov.uk services
Project-URL: Homepage, https://github.com/alixedi/fast-gov-uk
Project-URL: Repository, https://github.com/alixedi/fast-gov-uk
Project-URL: Issues, https://github.com/alixedi/fast-gov-uk/issues
Author-email: Ali Zaidi <alixedi@gmail.com>
License-Expression: MIT
License-File: LICENSE
Requires-Python: >=3.12
Requires-Dist: notifications-python-client>=10.0.1
Requires-Dist: python-fasthtml>=0.12.19
